{
    "selectedOs": "linux",
    "region": "all",
    "spot/onDemand": "spot",
    "apps": [
        {
            "app": "App1",
            "share": true,
            "components": [
                {
                    "memory": 15,
                    "vCPUs": 22,
                    "behavior": "terminate",
                    "anti-affinity": "Comp2",
                    "name": "Comp1"
                },
                {
                    "memory": 14,
                    "vCPUs": 22,
                    "behavior": "terminate",
                    "name": "Comp2"
                },
                {
                    "memory": 14,
                    "vCPUs": 22,
                    "behavior": "terminate",
                    "name": "Comp3"
                }
            ]
        }
    ]
}